README.md
setup.py
ziion.egg-info/PKG-INFO
ziion.egg-info/SOURCES.txt
ziion.egg-info/dependency_links.txt
ziion.egg-info/entry_points.txt
ziion.egg-info/requires.txt
ziion.egg-info/top_level.txt
ziion_cli/__init__.py
ziion_cli/__main__.py
ziion_cli/__version__.py
ziion_cli/cargo.py
ziion_cli/constants.py
ziion_cli/dispatcher.py
ziion_cli/solc_select.py
ziion_cli/utils.py
ziion_cli/ziion.py