Metadata-Version: 2.1
Name: ziion
Version: 1.0.8
Summary: ziion-cli provides an easy way to manage rust and solc packages for ARM and AMD.
Author: Halborn
